ss_logger/__init__.py
ss_logger-0.2.1.dist-info/WHEEL
ss_logger-0.2.1.dist-info/METADATA
ss_logger-0.2.1.dist-info/RECORD
