Metadata-Version: 2.1
Name: ss_logger
Version: 0.2.1
Summary: This is the ss_logger module.
Home-page: https://pypi.org/project/ss-logger/
Author: amitskidrow
Author-email: amitskidrow@gmail.com
Requires-Dist: snakecase
